norequests.py
no_requests-0.1.0.dist-info/licenses/LICENSE
no_requests-0.1.0.dist-info/METADATA
no_requests-0.1.0.dist-info/WHEEL
no_requests-0.1.0.dist-info/top_level.txt
no_requests-0.1.0.dist-info/RECORD
