Metadata-Version: 2.4
Name: no-requests
Version: 0.1.0
Summary: A lightweight, dependency-free, requests-like HTTP client with safe defaults
Home-page: https://github.com/gatopeich/no-requests
Author: gatopeich
Author-email: gatopeich <gatopeich@users.noreply.github.com>
License-Expression: MIT
Project-URL: Homepage, https://github.com/gatopeich/no-requests
Keywords: http,requests,standard library,no dependencies,lightweight
Classifier: Programming Language :: Python :: 3
Classifier: Operating System :: OS Independent
Requires-Python: >=3.6
License-File: LICENSE
Dynamic: author
Dynamic: home-page
Dynamic: license-file
Dynamic: requires-python
